<?xml version = '1.0' encoding = 'UTF-8'?>
<FKIndexAssociation class="oracle.dbtools.crest.model.design.relational.FKIndexAssociation" directorySegmentName="seg_0" id="95F058D5-1CD8-8BEF-4575-4526424A5F5E" containerWithKeyObject="19F45F26-43C9-F1A8-AE2E-4BF8DD466204" localFKIndex="0C1C3058-66FF-7806-FACA-E9CE9BD6D32E" name="FK_CONTACTO_PERSONA">
<sourceDDLFile>siac-db.ddl</sourceDDLFile>
<createdBy>quesadx</createdBy>
<createdTime>2026-05-05 17:23:17 UTC</createdTime>
<ownerDesignName>siac-db-diagram</ownerDesignName>
<importedID>E77DA84F-D6FC-0B90-0AE8-42B4C3423AE9</importedID>
<referredTableLongName>SIAC_PERSONA</referredTableLongName>
<deleteRule>NO ACTION</deleteRule>
<referredTableID>85A174CF-EE2D-2AA8-CCDC-494662BCABF9</referredTableID>
<keyObject>535AA93B-BCA7-E04E-5987-151485F54F5F</keyObject>
<referredKeyID>535AA93B-BCA7-E04E-5987-151485F54F5F</referredKeyID>
<mandatory>false</mandatory>
<refColNames>ID_PERSONA</refColNames>
<transferable>true</transferable>
<rely>false</rely>
<columnDependencyConstraintGenerateInDDL>true</columnDependencyConstraintGenerateInDDL>
</FKIndexAssociation>
